[
  {
    "title": "予約ボタンを押してもらうための7つの鍵--旅行サイトに欠かせない要素とは？",
    "url": "https://japan.cnet.com/article/20377830/",
    "description": "",
    "savedAt": "2008-07-29T14:46:23Z",
    "tags": [
      "Web",
      "travel",
      "Analytics",
      "marketing"
    ]
  },
  {
    "title": "zizo.jp",
    "url": "http://zizo.jp/maker/yaoi.html",
    "description": "",
    "savedAt": "2008-07-24T07:27:56Z",
    "tags": [
      "tools",
      "w"
    ]
  },
  {
    "title": "『まだあった、Smartyの高速化』",
    "url": "https://ameblo.jp/takuya/entry-10010110834.html",
    "description": "",
    "savedAt": "2008-07-17T05:04:46Z",
    "tags": [
      "Web",
      "IT"
    ]
  },
  {
    "title": "Smartyの読み込みコスト（時間）を削減する",
    "url": "http://code.xenophy.com/?p=73",
    "description": "",
    "savedAt": "2008-07-17T05:03:32Z",
    "tags": [
      "Web",
      "IT"
    ]
  },
  {
    "title": "日本一区二区三区免费播放视频站_亚洲高清揄拍自拍_在线亚洲欧美综合视频一区",
    "url": "http://www.kazuizm.com/2006/01/16-173531.php",
    "description": "",
    "savedAt": "2008-07-17T05:02:24Z",
    "tags": [
      "Web",
      "IT",
      "PHP",
      "tips"
    ]
  },
  {
    "title": "Tourism Australia Image Gallery",
    "url": "https://images.australia.com/",
    "description": "",
    "savedAt": "2008-07-17T04:50:35Z",
    "tags": [
      "Web",
      "travel",
      "images"
    ]
  },
  {
    "title": "http://www.comachi.com/2006/12/smarty_var_dumpprint_r.html",
    "url": "http://www.comachi.com/2006/12/smarty_var_dumpprint_r.html",
    "description": "me too.",
    "savedAt": "2008-07-04T07:38:48Z",
    "tags": [
      "Web",
      "IT",
      "PHP"
    ]
  },
  {
    "title": "YUI Compressorで簡単にjavascriptとCSSを圧縮 - Affamative Way",
    "url": "https://cos31.hatenablog.jp/entry/20080116/1200504657",
    "description": "",
    "savedAt": "2008-07-04T03:27:38Z",
    "tags": [
      "IT",
      "js",
      "Web"
    ]
  },
  {
    "title": "Clean CSS - A Resource for Web Designers - Optmize and Format your CSS",
    "url": "https://www.cleancss.com/",
    "description": "",
    "savedAt": "2008-07-03T08:10:59Z",
    "tags": [
      "Web",
      "css",
      "tools"
    ]
  },
  {
    "title": "JavaScript Compression - Compress JavaScript Code Free with this JavaScript Compressor (CSS Too) - from Creativyst",
    "url": "https://www.creativyst.com/Prod/3/",
    "description": "",
    "savedAt": "2008-07-03T07:58:28Z",
    "tags": [
      "Web",
      "IT",
      "js",
      "tools"
    ]
  },
  {
    "title": "https://www.julienlecomte.net/yuicompressor/",
    "url": "https://www.julienlecomte.net/yuicompressor/",
    "description": "",
    "savedAt": "2008-07-03T07:47:37Z",
    "tags": [
      "IT",
      "js",
      "Web"
    ]
  }
]