[
  {
    "title": "グリー内製新作『メダル オブ モンスターズ』はメダル連射が超爽快の新感覚ソーシャルゲーム - ファミ通.com",
    "url": "https://www.famitsu.com/news/201211/28025067.html",
    "description": "あれ、セガ…　あれ？ かぶった？",
    "savedAt": "2012-11-28T08:42:38Z",
    "tags": [
      "Game"
    ]
  },
  {
    "title": "MySQL update statement to store ranking positions",
    "url": "https://stackoverflow.com/questions/3196971/mysql-update-statement-to-store-ranking-positions",
    "description": "行を増やしながらアップデート",
    "savedAt": "2012-11-24T09:19:47Z",
    "tags": [
      "MySQL"
    ]
  },
  {
    "title": "いまさら聞けないSQL Server 2005のインデックス　その４「フルテキストインデックス」 - Bug Catharsis",
    "url": "https://zecl.hatenablog.com/entry/20080224/p2",
    "description": "",
    "savedAt": "2012-11-24T08:28:47Z",
    "tags": [
      "DB"
    ]
  },
  {
    "title": "MySQL :: MySQL Workbench",
    "url": "https://www.mysql.com/jp/products/workbench/",
    "description": "",
    "savedAt": "2012-11-24T07:44:13Z",
    "tags": [
      "MySQL"
    ]
  },
  {
    "title": "★『姫』を操り『兵士』をケリ飛ばせ！！★新ジャンル「アクションパズルRPG」！『パズル』のゲーム性に『RPG要素』をプラスした『ステージクリア型』のスマートフォンアプリ！",
    "url": "http://www.gungho.jp/kps/common/root/kps.html",
    "description": "ガウガウを初撃破! -さぁ今すぐあなたも蹴っ飛ばそう!!",
    "savedAt": "2012-11-20T03:47:17Z",
    "tags": []
  },
  {
    "title": "【動画】超力作がズラリ！　セガが今冬配信のスマホゲーム5タイトルを披露　 | ファミ通App【スマホゲーム情報サイト】",
    "url": "https://app.famitsu.com/20121119_110184/",
    "description": "ほらぁ",
    "savedAt": "2012-11-19T13:46:28Z",
    "tags": [
      "Game"
    ]
  },
  {
    "title": "スクエニプロデューサー安藤武博氏のブログ“スマゲ★革命”第三十回　「スマゲ革命序章、完結。」 | ファミ通App【スマホゲーム情報サイト】",
    "url": "https://app.famitsu.com/20121116_109633/",
    "description": "ブレイブリーデフォルトの件が、飛び火したのか思ってしまった、だめな僕",
    "savedAt": "2012-11-16T08:31:08Z",
    "tags": []
  },
  {
    "title": "阿・弥・陀",
    "url": "https://www.nintendo.co.jp/ds/dsiware/k9jj/index.html",
    "description": "",
    "savedAt": "2012-11-15T00:20:23Z",
    "tags": [
      "Game"
    ]
  },
  {
    "title": "巨大立方体を50万人が破壊していくゲーム « WIRED_.jp",
    "url": "http://cms2x.wired.jp/2012/11/12/curiosity/",
    "description": "",
    "savedAt": "2012-11-13T04:49:13Z",
    "tags": [
      "Game"
    ]
  },
  {
    "title": "「テーマがある人は、テーマなき人をどう使ってもいい」：日経ビジネスオンライン",
    "url": "http://business.nikkeibp.co.jp/article/interview/20121031/238838/",
    "description": "",
    "savedAt": "2012-11-13T02:35:14Z",
    "tags": [
      "interview",
      "movie"
    ]
  },
  {
    "title": "【G-STAR2012】期待のスマゲメーカー“Wemade”の新作タイトルを遊んできましたヨ！全部動画つき | ファミ通App【スマホゲーム情報サイト】",
    "url": "https://app.famitsu.com/20121112_108049/",
    "description": "",
    "savedAt": "2012-11-12T14:14:32Z",
    "tags": [
      "Game"
    ]
  },
  {
    "title": "http://ja.pokemon-gl.com/about/sp/ec2012/regulation.pdf",
    "url": "http://ja.pokemon-gl.com/about/sp/ec2012/regulation.pdf",
    "description": "特性のところで、さめはだイーブイを想像して吹く",
    "savedAt": "2012-11-11T01:21:53Z",
    "tags": [
      "Game"
    ]
  },
  {
    "title": "gooサービス終了のお知らせ | dメニュー",
    "url": "http://blog.goo.ne.jp/ameque/e/604e9c06d03062236e99c84448373905?fm=rss",
    "description": "からりすとのおもしろさ",
    "savedAt": "2012-11-11T00:49:34Z",
    "tags": [
      "Comic"
    ]
  },
  {
    "title": "iRSSの日記",
    "url": "https://hatena.blog/api/diary_redirect?path=/iRSS/searchdiary",
    "description": "",
    "savedAt": "2012-11-08T01:00:11Z",
    "tags": [
      "iOS"
    ]
  },
  {
    "title": "NetBeansで小文字から大文字変換と大文字から小文字変換とか",
    "url": "https://nishiaki.probo.jp/2010/12/netbeans.html",
    "description": "",
    "savedAt": "2012-11-07T05:59:08Z",
    "tags": [
      "PHP"
    ]
  },
  {
    "title": "「優秀な中間管理職」が壊れていく必然：日経ビジネスオンライン",
    "url": "http://business.nikkeibp.co.jp/article/interview/20121031/238837/",
    "description": "",
    "savedAt": "2012-11-05T07:24:45Z",
    "tags": [
      "interview",
      "movie"
    ]
  },
  {
    "title": "https://jp.techcrunch.com/2012/10/01/20120929five-big-changes-in-the-ios-6-app-store-and-what-developers-should-do/",
    "url": "https://jp.techcrunch.com/2012/10/01/20120929five-big-changes-in-the-ios-6-app-store-and-what-developers-should-do/",
    "description": "",
    "savedAt": "2012-11-05T04:39:47Z",
    "tags": [
      "iOS"
    ]
  },
  {
    "title": "パズル＆ドラゴンズに業界が騒然！「次の iPhone ゲーム」を作った男、山本大介氏インタビュー。 | AppBank",
    "url": "https://www.appbank.net/2012/04/11/iphone-news/395908.php",
    "description": "",
    "savedAt": "2012-11-05T00:39:26Z",
    "tags": [
      "Game"
    ]
  },
  {
    "title": "SVN update,commitをLinux cronで実行する場合の注意 | 技術ブログ",
    "url": "http://faz.main.jp/wp/%E6%9C%AA%E5%88%86%E9%A1%9E/201/",
    "description": "",
    "savedAt": "2012-11-02T04:54:25Z",
    "tags": [
      "Server"
    ]
  },
  {
    "title": "iOSのPush Notification < iPod touch < kei3.jp",
    "url": "http://www.kei3.jp/diary.php?id=8456",
    "description": "",
    "savedAt": "2012-11-01T02:34:19Z",
    "tags": [
      "iOS"
    ]
  },
  {
    "title": "APNSの複数クライアント送信 - ほげぐらまの別館",
    "url": "http://lain.heavy.jp/lain/2011/11/14/312",
    "description": "",
    "savedAt": "2012-11-01T02:17:35Z",
    "tags": [
      "iOS",
      "スマホ"
    ]
  }
]