{
  "books": [
    {
      "no": 1,
      "title": "重力の井戸の底で 機動戦士ガンダムUC(6) (角川文庫)",
      "url": "https://bookmeter.com/books/637625",
      "author": "福井　晴敏",
      "authorUrl": "https://bookmeter.com/search?author=%E7%A6%8F%E4%BA%95%E3%80%80%E6%99%B4%E6%95%8F",
      "thumb": "https://m.media-amazon.com/images/I/51Gecv7oDHL._SL500_.jpg",
      "date": "2010/09/30"
    },
    {
      "no": 2,
      "title": "小説・料理の鉄人〈2〉陳建一対フレンチの刺客 (扶桑社文庫)",
      "url": "https://bookmeter.com/books/12658",
      "author": "小山 薫堂",
      "authorUrl": "https://bookmeter.com/search?author=%E5%B0%8F%E5%B1%B1+%E8%96%AB%E5%A0%82",
      "thumb": "https://m.media-amazon.com/images/I/5109BXDotHL._SL500_.jpg",
      "date": "2010/09/30"
    },
    {
      "no": 3,
      "title": "マンガの描き方: 似顔絵から長編まで (知恵の森文庫)",
      "url": "https://bookmeter.com/books/547430",
      "author": "手塚 治虫",
      "authorUrl": "https://bookmeter.com/search?author=%E6%89%8B%E5%A1%9A+%E6%B2%BB%E8%99%AB",
      "thumb": "https://m.media-amazon.com/images/I/51JNDqudGYL._SL500_.jpg",
      "date": "2010/09/28"
    },
    {
      "no": 4,
      "title": "狂い咲く薔薇を君に: 牧場智久の雑役 (光文社文庫 た 21-5)",
      "url": "https://bookmeter.com/books/525341",
      "author": "竹本 健治",
      "authorUrl": "https://bookmeter.com/search?author=%E7%AB%B9%E6%9C%AC+%E5%81%A5%E6%B2%BB",
      "thumb": "https://m.media-amazon.com/images/I/51cYJ5kbKUL._SL500_.jpg",
      "date": "2010/09/22"
    },
    {
      "no": 5,
      "title": "ブレイブ・ストーリー (下)",
      "url": "https://bookmeter.com/books/579941",
      "author": "宮部 みゆき",
      "authorUrl": "https://bookmeter.com/search?author=%E5%AE%AE%E9%83%A8+%E3%81%BF%E3%82%86%E3%81%8D",
      "thumb": "https://m.media-amazon.com/images/I/61YexAgUmlL._SL500_.jpg",
      "date": "2010/09/15"
    },
    {
      "no": 6,
      "title": "ブレイブ・ストーリー (中)",
      "url": "https://bookmeter.com/books/579940",
      "author": "宮部 みゆき",
      "authorUrl": "https://bookmeter.com/search?author=%E5%AE%AE%E9%83%A8+%E3%81%BF%E3%82%86%E3%81%8D",
      "thumb": "https://m.media-amazon.com/images/I/61C2B9cfqAL._SL500_.jpg",
      "date": "2010/09/15"
    },
    {
      "no": 7,
      "title": "スターダスト★ウインク 3 (りぼんマスコットコミックス)",
      "url": "https://bookmeter.com/books/536645",
      "author": "春田 なな",
      "authorUrl": "https://bookmeter.com/search?author=%E6%98%A5%E7%94%B0+%E3%81%AA%E3%81%AA",
      "thumb": "https://m.media-amazon.com/images/I/412FAEv5QFL._SL500_.jpg",
      "date": "2010/09/12"
    },
    {
      "no": 8,
      "title": "スターダスト★ウインク 2 (りぼんマスコットコミックス)",
      "url": "https://bookmeter.com/books/576382",
      "author": "春田 なな",
      "authorUrl": "https://bookmeter.com/search?author=%E6%98%A5%E7%94%B0+%E3%81%AA%E3%81%AA",
      "thumb": "https://m.media-amazon.com/images/I/51dXg-dmaEL._SL500_.jpg",
      "date": "2010/09/12"
    },
    {
      "no": 9,
      "title": "じーさん武勇伝 (講談社文庫)",
      "url": "https://bookmeter.com/books/512843",
      "author": "竹内 真",
      "authorUrl": "https://bookmeter.com/search?author=%E7%AB%B9%E5%86%85+%E7%9C%9F",
      "thumb": "https://m.media-amazon.com/images/I/414G72NZ4CL._SL500_.jpg",
      "date": "2010/09/06"
    },
    {
      "no": 10,
      "title": "どろろ〈下〉 (朝日文庫)",
      "url": "https://bookmeter.com/books/69674",
      "author": "手塚 治虫,NAKA雅MURA",
      "authorUrl": "https://bookmeter.com/search?author=%E6%89%8B%E5%A1%9A+%E6%B2%BB%E8%99%AB%2CNAKA%E9%9B%85MURA",
      "thumb": "https://m.media-amazon.com/images/I/5137GVS86ZL._SL500_.jpg",
      "date": "2010/09/02"
    },
    {
      "no": 11,
      "title": "どろろ 上 (朝日文庫 て 3-3)",
      "url": "https://bookmeter.com/books/69673",
      "author": "手塚 治虫,NAKA雅MURA",
      "authorUrl": "https://bookmeter.com/search?author=%E6%89%8B%E5%A1%9A+%E6%B2%BB%E8%99%AB%2CNAKA%E9%9B%85MURA",
      "thumb": "https://m.media-amazon.com/images/I/512MGG3BVQL._SL500_.jpg",
      "date": "2010/09/02"
    },
    {
      "no": 12,
      "title": "スターダスト★ウインク 1 (りぼんマスコットコミックス)",
      "url": "https://bookmeter.com/books/565463",
      "author": "春田 なな",
      "authorUrl": "https://bookmeter.com/search?author=%E6%98%A5%E7%94%B0+%E3%81%AA%E3%81%AA",
      "thumb": "https://m.media-amazon.com/images/I/51VWAEkqmUL._SL500_.jpg",
      "date": "2010/09/01"
    }
  ],
  "count": 12,
  "totalCount": 0,
  "totalPages": 0,
  "totalReviews": 0,
  "totalNice": 0
}