{
  "books": [
    {
      "no": 1,
      "title": "動物農場: おとぎばなし (岩波文庫 赤 262-4)",
      "url": "https://bookmeter.com/books/573334",
      "author": "ジョージ オーウェル",
      "authorUrl": "https://bookmeter.com/search?author=%E3%82%B8%E3%83%A7%E3%83%BC%E3%82%B8+%E3%82%AA%E3%83%BC%E3%82%A6%E3%82%A7%E3%83%AB",
      "thumb": "https://m.media-amazon.com/images/I/51goltAHL4L._SL500_.jpg",
      "date": "2011/06/29"
    },
    {
      "no": 2,
      "title": "ハーモニー (ハヤカワ文庫 JA イ 7-2)",
      "url": "https://bookmeter.com/books/964244",
      "author": "伊藤 計劃",
      "authorUrl": "https://bookmeter.com/search?author=%E4%BC%8A%E8%97%A4+%E8%A8%88%E5%8A%83",
      "thumb": "https://m.media-amazon.com/images/I/21TK2NKl9pL._SL500_.jpg",
      "date": "2011/06/28"
    },
    {
      "no": 3,
      "title": "虐殺器官 (ハヤカワ文庫 JA イ 7-1)",
      "url": "https://bookmeter.com/books/565343",
      "author": "伊藤 計劃",
      "authorUrl": "https://bookmeter.com/search?author=%E4%BC%8A%E8%97%A4+%E8%A8%88%E5%8A%83",
      "thumb": "https://m.media-amazon.com/images/I/41bLE1PSrJL._SL500_.jpg",
      "date": "2011/06/23"
    },
    {
      "no": 4,
      "title": "死亡フラグが立ちました! (宝島社文庫) (宝島社文庫 C な 5-1)",
      "url": "https://bookmeter.com/books/604658",
      "author": "七尾 与史",
      "authorUrl": "https://bookmeter.com/search?author=%E4%B8%83%E5%B0%BE+%E4%B8%8E%E5%8F%B2",
      "thumb": "https://m.media-amazon.com/images/I/51u-81XBTTL._SL500_.jpg",
      "date": "2011/06/17"
    },
    {
      "no": 5,
      "title": "快楽なくして何が人生 (幻冬舎新書 た 2-1)",
      "url": "https://bookmeter.com/books/45320",
      "author": "団 鬼六",
      "authorUrl": "https://bookmeter.com/search?author=%E5%9B%A3+%E9%AC%BC%E5%85%AD",
      "thumb": "https://m.media-amazon.com/images/I/51miVcDeknL._SL500_.jpg",
      "date": "2011/06/15"
    },
    {
      "no": 6,
      "title": "喜婚男と避婚男 (新潮新書 420)",
      "url": "https://bookmeter.com/books/3273504",
      "author": "ツノダ姉妹",
      "authorUrl": "https://bookmeter.com/search?author=%E3%83%84%E3%83%8E%E3%83%80%E5%A7%89%E5%A6%B9",
      "thumb": "https://m.media-amazon.com/images/I/41aEexKl4ZL._SL500_.jpg",
      "date": "2011/06/14"
    },
    {
      "no": 7,
      "title": "トイレのない旅 (講談社文庫 ほ 23-1)",
      "url": "https://bookmeter.com/books/105871",
      "author": "星野 知子",
      "authorUrl": "https://bookmeter.com/search?author=%E6%98%9F%E9%87%8E+%E7%9F%A5%E5%AD%90",
      "thumb": "https://m.media-amazon.com/images/I/41hNJePDA8L._SL500_.jpg",
      "date": "2011/06/14"
    },
    {
      "no": 8,
      "title": "物理学の原理と法則 (PHPサイエンス・ワールド新書)",
      "url": "https://bookmeter.com/books/3166173",
      "author": "池内 了",
      "authorUrl": "https://bookmeter.com/search?author=%E6%B1%A0%E5%86%85+%E4%BA%86",
      "thumb": "https://m.media-amazon.com/images/I/41+EWHcNTgL._SL500_.jpg",
      "date": "2011/06/07"
    },
    {
      "no": 9,
      "title": "祓魔師な嫁ですが。　第２巻 　 　 (あすかコミックスDX)",
      "url": "https://bookmeter.com/books/2080984",
      "author": "風都　ノリ",
      "authorUrl": "https://bookmeter.com/search?author=%E9%A2%A8%E9%83%BD%E3%80%80%E3%83%8E%E3%83%AA",
      "thumb": "https://m.media-amazon.com/images/I/61h-XrHkzcL._SL500_.jpg",
      "date": "2011/06/05"
    },
    {
      "no": 10,
      "title": "祓魔師な嫁ですが。　第１巻 (あすかコミックスDX)",
      "url": "https://bookmeter.com/books/636318",
      "author": "風都　ノリ",
      "authorUrl": "https://bookmeter.com/search?author=%E9%A2%A8%E9%83%BD%E3%80%80%E3%83%8E%E3%83%AA",
      "thumb": "https://m.media-amazon.com/images/I/513sgBih-6L._SL500_.jpg",
      "date": "2011/06/05"
    },
    {
      "no": 11,
      "title": "虹の彼方に（下）　機動戦士ガンダムＵＣ（１０） (角川文庫 ふ 24-59 機動戦士ガンダムUC 10)",
      "url": "https://bookmeter.com/books/3166035",
      "author": "福井　晴敏",
      "authorUrl": "https://bookmeter.com/search?author=%E7%A6%8F%E4%BA%95%E3%80%80%E6%99%B4%E6%95%8F",
      "thumb": "https://m.media-amazon.com/images/I/41bE9JPu0CL._SL500_.jpg",
      "date": "2011/06/01"
    }
  ],
  "count": 11,
  "totalCount": 0,
  "totalPages": 0,
  "totalReviews": 0,
  "totalNice": 0
}