{
  "books": [
    {
      "no": 1,
      "title": "ロボット21世紀 (文春新書 179)",
      "url": "https://bookmeter.com/books/480873",
      "author": "瀬名 秀明",
      "authorUrl": "https://bookmeter.com/search?author=%E7%80%AC%E5%90%8D+%E7%A7%80%E6%98%8E",
      "thumb": "https://m.media-amazon.com/images/I/412PI-zDC7L._SL500_.jpg",
      "date": "2010/07/29"
    },
    {
      "no": 2,
      "title": "鋼の錬金術師(22) (ガンガンコミックス)",
      "url": "https://bookmeter.com/books/580420",
      "author": "荒川 弘",
      "authorUrl": "https://bookmeter.com/search?author=%E8%8D%92%E5%B7%9D+%E5%BC%98",
      "thumb": "https://m.media-amazon.com/images/I/519KQnCu+1L._SL500_.jpg",
      "date": "2010/07/26"
    },
    {
      "no": 3,
      "title": "鋼の錬金術師(21) (ガンガンコミックス)",
      "url": "https://bookmeter.com/books/580484",
      "author": "荒川 弘",
      "authorUrl": "https://bookmeter.com/search?author=%E8%8D%92%E5%B7%9D+%E5%BC%98",
      "thumb": "https://m.media-amazon.com/images/I/51Ot6QK552L._SL500_.jpg",
      "date": "2010/07/26"
    },
    {
      "no": 4,
      "title": "死体は悩む: 多発する猟奇殺人事件の真実 (角川oneテーマ21 C 137)",
      "url": "https://bookmeter.com/books/17817",
      "author": "上野 正彦",
      "authorUrl": "https://bookmeter.com/search?author=%E4%B8%8A%E9%87%8E+%E6%AD%A3%E5%BD%A6",
      "thumb": "https://m.media-amazon.com/images/I/41FGEJB6soL._SL500_.jpg",
      "date": "2010/07/26"
    },
    {
      "no": 5,
      "title": "山伏地蔵坊の放浪 (創元推理文庫) (創元推理文庫 M あ 2-4)",
      "url": "https://bookmeter.com/books/550164",
      "author": "有栖川 有栖",
      "authorUrl": "https://bookmeter.com/search?author=%E6%9C%89%E6%A0%96%E5%B7%9D+%E6%9C%89%E6%A0%96",
      "thumb": "https://m.media-amazon.com/images/I/51eVqMVOAlL._SL500_.jpg",
      "date": "2010/07/26"
    },
    {
      "no": 6,
      "title": "堕ちていく僕たち (集英社文庫)",
      "url": "https://bookmeter.com/books/562652",
      "author": "森 博嗣",
      "authorUrl": "https://bookmeter.com/search?author=%E6%A3%AE+%E5%8D%9A%E5%97%A3",
      "thumb": "https://m.media-amazon.com/images/I/41ktmUcVqGL._SL500_.jpg",
      "date": "2010/07/20"
    },
    {
      "no": 7,
      "title": "ニッポンの海外旅行 若者と観光メディアの50年史 (ちくま新書 854)",
      "url": "https://bookmeter.com/books/612859",
      "author": "山口 誠",
      "authorUrl": "https://bookmeter.com/search?author=%E5%B1%B1%E5%8F%A3+%E8%AA%A0",
      "thumb": "https://m.media-amazon.com/images/I/41w2AmRBLpL._SL500_.jpg",
      "date": "2010/07/20"
    },
    {
      "no": 8,
      "title": "NOVA 2---書き下ろし日本ＳＦコレクション (河出文庫)",
      "url": "https://bookmeter.com/books/603729",
      "author": "東 浩紀,恩田 陸,法月 綸太郎,宮部 みゆき,神林 長平,倉田 タカシ,小路 幸也,新城 カズマ,曽根 圭介,田辺 青蛙,津原 泰水,西崎 憲",
      "authorUrl": "https://bookmeter.com/search?author=%E6%9D%B1+%E6%B5%A9%E7%B4%80%2C%E6%81%A9%E7%94%B0+%E9%99%B8%2C%E6%B3%95%E6%9C%88+%E7%B6%B8%E5%A4%AA%E9%83%8E%2C%E5%AE%AE%E9%83%A8+%E3%81%BF%E3%82%86%E3%81%8D%2C%E7%A5%9E%E6%9E%97+%E9%95%B7%E5%B9%B3%2C%E5%80%89%E7%94%B0+%E3%82%BF%E3%82%AB%E3%82%B7%2C%E5%B0%8F%E8%B7%AF+%E5%B9%B8%E4%B9%9F%2C%E6%96%B0%E5%9F%8E+%E3%82%AB%E3%82%BA%E3%83%9E%2C%E6%9B%BD%E6%A0%B9+%E5%9C%AD%E4%BB%8B%2C%E7%94%B0%E8%BE%BA+%E9%9D%92%E8%9B%99%2C%E6%B4%A5%E5%8E%9F+%E6%B3%B0%E6%B0%B4%2C%E8%A5%BF%E5%B4%8E+%E6%86%B2",
      "thumb": "https://m.media-amazon.com/images/I/51hNJMIB9DL._SL500_.jpg",
      "date": "2010/07/20"
    },
    {
      "no": 9,
      "title": "NOVA 1---書き下ろし日本SFコレクション (河出文庫 お 20-1 書き下ろし日本SFコレクション)",
      "url": "https://bookmeter.com/books/290224",
      "author": "伊藤 計劃,円城 塔,北野 勇作,小林 泰三,斉藤 直子,田中 哲弥,田中 啓文,飛 浩隆,藤田 雅矢,牧野 修,山本 弘",
      "authorUrl": "https://bookmeter.com/search?author=%E4%BC%8A%E8%97%A4+%E8%A8%88%E5%8A%83%2C%E5%86%86%E5%9F%8E+%E5%A1%94%2C%E5%8C%97%E9%87%8E+%E5%8B%87%E4%BD%9C%2C%E5%B0%8F%E6%9E%97+%E6%B3%B0%E4%B8%89%2C%E6%96%89%E8%97%A4+%E7%9B%B4%E5%AD%90%2C%E7%94%B0%E4%B8%AD+%E5%93%B2%E5%BC%A5%2C%E7%94%B0%E4%B8%AD+%E5%95%93%E6%96%87%2C%E9%A3%9B+%E6%B5%A9%E9%9A%86%2C%E8%97%A4%E7%94%B0+%E9%9B%85%E7%9F%A2%2C%E7%89%A7%E9%87%8E+%E4%BF%AE%2C%E5%B1%B1%E6%9C%AC+%E5%BC%98",
      "thumb": "https://m.media-amazon.com/images/I/51j4buUScAL._SL500_.jpg",
      "date": "2010/07/13"
    },
    {
      "no": 10,
      "title": "キャラクターメーカー6つの理論とワークショップで学ぶ「つくり方」 (アスキー新書 62)",
      "url": "https://bookmeter.com/books/558562",
      "author": "大塚 英志",
      "authorUrl": "https://bookmeter.com/search?author=%E5%A4%A7%E5%A1%9A+%E8%8B%B1%E5%BF%97",
      "thumb": "https://m.media-amazon.com/images/I/41IlxNPrwIL._SL500_.jpg",
      "date": "2010/07/13"
    },
    {
      "no": 11,
      "title": "なぜ宇宙人は地球に来ない? (PHP新書 600)",
      "url": "https://bookmeter.com/books/530976",
      "author": "松尾 貴史",
      "authorUrl": "https://bookmeter.com/search?author=%E6%9D%BE%E5%B0%BE+%E8%B2%B4%E5%8F%B2",
      "thumb": "https://m.media-amazon.com/images/I/51357eJ0AnL._SL500_.jpg",
      "date": "2010/07/13"
    },
    {
      "no": 12,
      "title": "鋼の錬金術師(20) (ガンガンコミックス)",
      "url": "https://bookmeter.com/books/566544",
      "author": "荒川 弘",
      "authorUrl": "https://bookmeter.com/search?author=%E8%8D%92%E5%B7%9D+%E5%BC%98",
      "thumb": "https://m.media-amazon.com/images/I/51L0iiW-FKL._SL500_.jpg",
      "date": "2010/07/03"
    },
    {
      "no": 13,
      "title": "鋼の錬金術師(19) (ガンガンコミックス)",
      "url": "https://bookmeter.com/books/580418",
      "author": "荒川 弘",
      "authorUrl": "https://bookmeter.com/search?author=%E8%8D%92%E5%B7%9D+%E5%BC%98",
      "thumb": "https://m.media-amazon.com/images/I/51SK7ojbsDL._SL500_.jpg",
      "date": "2010/07/03"
    },
    {
      "no": 14,
      "title": "鋼の錬金術師(18) (ガンガンコミックス)",
      "url": "https://bookmeter.com/books/566542",
      "author": "荒川 弘",
      "authorUrl": "https://bookmeter.com/search?author=%E8%8D%92%E5%B7%9D+%E5%BC%98",
      "thumb": "https://m.media-amazon.com/images/I/51aHGtiaZ0L._SL500_.jpg",
      "date": "2010/07/03"
    },
    {
      "no": 15,
      "title": "鋼の錬金術師(17) (ガンガンコミックス)",
      "url": "https://bookmeter.com/books/580416",
      "author": "荒川 弘",
      "authorUrl": "https://bookmeter.com/search?author=%E8%8D%92%E5%B7%9D+%E5%BC%98",
      "thumb": "https://m.media-amazon.com/images/I/51viRy6-oqL._SL500_.jpg",
      "date": "2010/07/03"
    },
    {
      "no": 16,
      "title": "鋼の錬金術師(16) (ガンガンコミックス)",
      "url": "https://bookmeter.com/books/566541",
      "author": "荒川 弘",
      "authorUrl": "https://bookmeter.com/search?author=%E8%8D%92%E5%B7%9D+%E5%BC%98",
      "thumb": "https://m.media-amazon.com/images/I/51GxoMF-8wL._SL500_.jpg",
      "date": "2010/07/03"
    },
    {
      "no": 17,
      "title": "鋼の錬金術師(15) (ガンガンコミックス)",
      "url": "https://bookmeter.com/books/566539",
      "author": "荒川 弘",
      "authorUrl": "https://bookmeter.com/search?author=%E8%8D%92%E5%B7%9D+%E5%BC%98",
      "thumb": "https://m.media-amazon.com/images/I/51AQwpqkwHL._SL500_.jpg",
      "date": "2010/07/03"
    },
    {
      "no": 18,
      "title": "鋼の錬金術師(14)",
      "url": "https://bookmeter.com/books/580579",
      "author": "荒川 弘",
      "authorUrl": "https://bookmeter.com/search?author=%E8%8D%92%E5%B7%9D+%E5%BC%98",
      "thumb": "https://m.media-amazon.com/images/I/51Z1FFNZ9HL._SL500_.jpg",
      "date": "2010/07/03"
    },
    {
      "no": 19,
      "title": "鋼の錬金術師 13",
      "url": "https://bookmeter.com/books/566538",
      "author": "荒川 弘",
      "authorUrl": "https://bookmeter.com/search?author=%E8%8D%92%E5%B7%9D+%E5%BC%98",
      "thumb": "https://m.media-amazon.com/images/I/51VqioMI4CL._SL500_.jpg",
      "date": "2010/07/03"
    },
    {
      "no": 20,
      "title": "鋼の錬金術師(12) (ガンガンコミックス)",
      "url": "https://bookmeter.com/books/566537",
      "author": "荒川 弘",
      "authorUrl": "https://bookmeter.com/search?author=%E8%8D%92%E5%B7%9D+%E5%BC%98",
      "thumb": "https://m.media-amazon.com/images/I/51MDVTCQN1L._SL500_.jpg",
      "date": "2010/07/03"
    },
    {
      "no": 21,
      "title": "鋼の錬金術師(11) (ガンガンコミックス)",
      "url": "https://bookmeter.com/books/566536",
      "author": "荒川 弘",
      "authorUrl": "https://bookmeter.com/search?author=%E8%8D%92%E5%B7%9D+%E5%BC%98",
      "thumb": "https://m.media-amazon.com/images/I/51iw1UGSXSL._SL500_.jpg",
      "date": "2010/07/03"
    },
    {
      "no": 22,
      "title": "鋼の錬金術師 (10)",
      "url": "https://bookmeter.com/books/566535",
      "author": "荒川 弘",
      "authorUrl": "https://bookmeter.com/search?author=%E8%8D%92%E5%B7%9D+%E5%BC%98",
      "thumb": "https://m.media-amazon.com/images/I/51+d7aUEruL._SL500_.jpg",
      "date": "2010/07/03"
    },
    {
      "no": 23,
      "title": "鋼の錬金術師 (9)",
      "url": "https://bookmeter.com/books/566534",
      "author": "荒川 弘",
      "authorUrl": "https://bookmeter.com/search?author=%E8%8D%92%E5%B7%9D+%E5%BC%98",
      "thumb": "https://m.media-amazon.com/images/I/51KUs4LUm-L._SL500_.jpg",
      "date": "2010/07/03"
    },
    {
      "no": 24,
      "title": "鋼の錬金術師 (8)",
      "url": "https://bookmeter.com/books/566533",
      "author": "荒川 弘",
      "authorUrl": "https://bookmeter.com/search?author=%E8%8D%92%E5%B7%9D+%E5%BC%98",
      "thumb": "https://m.media-amazon.com/images/I/51NKudrrkAL._SL500_.jpg",
      "date": "2010/07/03"
    },
    {
      "no": 25,
      "title": "鋼の錬金術師(7)",
      "url": "https://bookmeter.com/books/566532",
      "author": "荒川 弘",
      "authorUrl": "https://bookmeter.com/search?author=%E8%8D%92%E5%B7%9D+%E5%BC%98",
      "thumb": "https://m.media-amazon.com/images/I/51hdsKcsZLL._SL500_.jpg",
      "date": "2010/07/03"
    },
    {
      "no": 26,
      "title": "鋼の錬金術師(6) (ガンガンコミックス)",
      "url": "https://bookmeter.com/books/566531",
      "author": "荒川 弘",
      "authorUrl": "https://bookmeter.com/search?author=%E8%8D%92%E5%B7%9D+%E5%BC%98",
      "thumb": "https://m.media-amazon.com/images/I/51CCbz4DjjL._SL500_.jpg",
      "date": "2010/07/03"
    },
    {
      "no": 27,
      "title": "鋼の錬金術師(5) (ガンガンコミックス)",
      "url": "https://bookmeter.com/books/566529",
      "author": "荒川 弘",
      "authorUrl": "https://bookmeter.com/search?author=%E8%8D%92%E5%B7%9D+%E5%BC%98",
      "thumb": "https://m.media-amazon.com/images/I/517qBoUIOZL._SL500_.jpg",
      "date": "2010/07/03"
    },
    {
      "no": 28,
      "title": "鋼の錬金術師(4) (ガンガンコミックス)",
      "url": "https://bookmeter.com/books/566528",
      "author": "荒川 弘",
      "authorUrl": "https://bookmeter.com/search?author=%E8%8D%92%E5%B7%9D+%E5%BC%98",
      "thumb": "https://m.media-amazon.com/images/I/510Je0cC0rL._SL500_.jpg",
      "date": "2010/07/03"
    },
    {
      "no": 29,
      "title": "鋼の錬金術師(3) (ガンガンコミックス)",
      "url": "https://bookmeter.com/books/566527",
      "author": "荒川 弘",
      "authorUrl": "https://bookmeter.com/search?author=%E8%8D%92%E5%B7%9D+%E5%BC%98",
      "thumb": "https://m.media-amazon.com/images/I/51VSlO3V8WL._SL500_.jpg",
      "date": "2010/07/03"
    },
    {
      "no": 30,
      "title": "鋼の錬金術師(2) (ガンガンコミックス)",
      "url": "https://bookmeter.com/books/566526",
      "author": "荒川 弘",
      "authorUrl": "https://bookmeter.com/search?author=%E8%8D%92%E5%B7%9D+%E5%BC%98",
      "thumb": "https://m.media-amazon.com/images/I/51iI5rNydlL._SL500_.jpg",
      "date": "2010/07/03"
    },
    {
      "no": 31,
      "title": "鋼の錬金術師(1) (ガンガンコミックス)",
      "url": "https://bookmeter.com/books/566524",
      "author": "荒川 弘",
      "authorUrl": "https://bookmeter.com/search?author=%E8%8D%92%E5%B7%9D+%E5%BC%98",
      "thumb": "https://m.media-amazon.com/images/I/51Nj8j-sXyL._SL500_.jpg",
      "date": "2010/07/03"
    },
    {
      "no": 32,
      "title": "鉄鍋のジャン!R 10: 頂上作戦 (少年チャンピオン・コミックス)",
      "url": "https://bookmeter.com/books/491605",
      "author": "西条 真二",
      "authorUrl": "https://bookmeter.com/search?author=%E8%A5%BF%E6%9D%A1+%E7%9C%9F%E4%BA%8C",
      "thumb": "https://m.media-amazon.com/images/I/61mwT+-VWYL._SL500_.jpg",
      "date": "2010/07/03"
    },
    {
      "no": 33,
      "title": "鉄鍋のジャン!R 9: 頂上作戦 (少年チャンピオン・コミックス)",
      "url": "https://bookmeter.com/books/491604",
      "author": "西条 真二",
      "authorUrl": "https://bookmeter.com/search?author=%E8%A5%BF%E6%9D%A1+%E7%9C%9F%E4%BA%8C",
      "thumb": "https://m.media-amazon.com/images/I/51D5jkgBikL._SL500_.jpg",
      "date": "2010/07/03"
    },
    {
      "no": 34,
      "title": "鉄鍋のジャン!R 8: 頂上作戦 (少年チャンピオン・コミックス)",
      "url": "https://bookmeter.com/books/491603",
      "author": "西条 真二",
      "authorUrl": "https://bookmeter.com/search?author=%E8%A5%BF%E6%9D%A1+%E7%9C%9F%E4%BA%8C",
      "thumb": "https://m.media-amazon.com/images/I/614wcEJwttL._SL500_.jpg",
      "date": "2010/07/03"
    },
    {
      "no": 35,
      "title": "鉄鍋のジャン!R 7: 頂上作戦 (少年チャンピオン・コミックス)",
      "url": "https://bookmeter.com/books/388471",
      "author": "西条 真二",
      "authorUrl": "https://bookmeter.com/search?author=%E8%A5%BF%E6%9D%A1+%E7%9C%9F%E4%BA%8C",
      "thumb": "https://m.media-amazon.com/images/I/51jdU9LRc3L._SL500_.jpg",
      "date": "2010/07/03"
    },
    {
      "no": 36,
      "title": "鉄鍋のジャン!R 6: 頂上作戦 (少年チャンピオン・コミックス)",
      "url": "https://bookmeter.com/books/452605",
      "author": "西条 真二",
      "authorUrl": "https://bookmeter.com/search?author=%E8%A5%BF%E6%9D%A1+%E7%9C%9F%E4%BA%8C",
      "thumb": "https://m.media-amazon.com/images/I/612nXlTEuhL._SL500_.jpg",
      "date": "2010/07/03"
    },
    {
      "no": 37,
      "title": "鉄鍋のジャン!R 5: 頂上作戦 (少年チャンピオン・コミックス)",
      "url": "https://bookmeter.com/books/491602",
      "author": "西条 真二",
      "authorUrl": "https://bookmeter.com/search?author=%E8%A5%BF%E6%9D%A1+%E7%9C%9F%E4%BA%8C",
      "thumb": "https://m.media-amazon.com/images/I/51jqa9kJSWL._SL500_.jpg",
      "date": "2010/07/03"
    },
    {
      "no": 38,
      "title": "鉄鍋のジャン!R 4: 頂上作戦 (少年チャンピオン・コミックス)",
      "url": "https://bookmeter.com/books/491601",
      "author": "西条 真二",
      "authorUrl": "https://bookmeter.com/search?author=%E8%A5%BF%E6%9D%A1+%E7%9C%9F%E4%BA%8C",
      "thumb": "https://m.media-amazon.com/images/I/512jHB5B6DL._SL500_.jpg",
      "date": "2010/07/03"
    },
    {
      "no": 39,
      "title": "鉄鍋のジャン!R 頂上作戦 3 (3) (少年チャンピオン・コミックス)",
      "url": "https://bookmeter.com/books/491600",
      "author": "西条 真二",
      "authorUrl": "https://bookmeter.com/search?author=%E8%A5%BF%E6%9D%A1+%E7%9C%9F%E4%BA%8C",
      "thumb": "https://m.media-amazon.com/images/I/51UMtnje3ML._SL500_.jpg",
      "date": "2010/07/03"
    },
    {
      "no": 40,
      "title": "鉄鍋のジャン!R ―頂上作戦 2 (少年チャンピオン・コミックス)",
      "url": "https://bookmeter.com/books/491599",
      "author": "西条 真二",
      "authorUrl": "https://bookmeter.com/search?author=%E8%A5%BF%E6%9D%A1+%E7%9C%9F%E4%BA%8C",
      "thumb": "https://m.media-amazon.com/images/I/61U91JM7r1L._SL500_.jpg",
      "date": "2010/07/03"
    },
    {
      "no": 41,
      "title": "鉄鍋のジャン!R 頂上作戦 (1) (少年チャンピオンコミックス)",
      "url": "https://bookmeter.com/books/435964",
      "author": "西条 真二",
      "authorUrl": "https://bookmeter.com/search?author=%E8%A5%BF%E6%9D%A1+%E7%9C%9F%E4%BA%8C",
      "thumb": "https://m.media-amazon.com/images/I/41Zo1KH0OuL._SL500_.jpg",
      "date": "2010/07/03"
    },
    {
      "no": 42,
      "title": "臨場 スペシャルブック (光文社文庫)",
      "url": "https://bookmeter.com/books/551641",
      "author": "横山 秀夫",
      "authorUrl": "https://bookmeter.com/search?author=%E6%A8%AA%E5%B1%B1+%E7%A7%80%E5%A4%AB",
      "thumb": "https://m.media-amazon.com/images/I/41hhAZeP4ZL._SL500_.jpg",
      "date": "2010/07/01"
    },
    {
      "no": 43,
      "title": "臨場 (光文社文庫 よ 14-1)",
      "url": "https://bookmeter.com/books/578282",
      "author": "横山 秀夫",
      "authorUrl": "https://bookmeter.com/search?author=%E6%A8%AA%E5%B1%B1+%E7%A7%80%E5%A4%AB",
      "thumb": "https://m.media-amazon.com/images/I/51cLtNZqDvL._SL500_.jpg",
      "date": "2010/07/01"
    }
  ],
  "count": 43,
  "totalCount": 0,
  "totalPages": 0,
  "totalReviews": 0,
  "totalNice": 0
}